[
  {
    "kind": "bash",
    "toolCallId": "call_mEed049eYIogSuNEXl0hzi4G",
    "command": "find ios -maxdepth 3 -type f \\( -name '*Tests.swift' -o -name 'project.yml' -o -name '*.swift' \\) | sort | head -80",
    "exitCode": 0,
    "outputSnippet": "ios/PrivateMoments/Models/MomentEditMediaItem.swift\nios/PrivateMoments/Models/OutboxOperation.swift\nios/PrivateMoments/Models/StorageStats.swift\nios/PrivateMoments/Models/TimelinePost.swift\nios/PrivateMoments/Networking/APIClient.swift\nios/PrivateMoments/Networking/APIModels.swift\nios/PrivateMoments/Networking/AppSettings.swift\nios/PrivateMoments/Networking/ImageCompression.swift\nios/PrivateMoments/Networking/KeychainStore.swift\nios/PrivateMoments/Persistence/AppDirectories.swift\nios/PrivateMome",
    "timestamp": 1777485273249
  },
  {
    "kind": "bash",
    "toolCallId": "call_72bPtOUsvZvh1cHXDY2EHKwX",
    "command": "test -f project.yml && printf exists || true",
    "exitCode": 0,
    "outputSnippet": "exists",
    "timestamp": 1777485278110
  },
  {
    "kind": "bash",
    "toolCallId": "call_GI9IpnNCLVIpPcQfa63INBSN",
    "command": "test -e ios/PrivateMoments/Views/PlainTextListEditor.swift && echo exists || echo missing",
    "exitCode": 0,
    "outputSnippet": "missing\n",
    "timestamp": 1777485282917
  },
  {
    "kind": "bash",
    "toolCallId": "call_WLW6oeFKMyJR2Mx8EMxWKqRb",
    "command": "test -e ios/PrivateMomentsListContinuationTests/PlainTextListContinuationTests.swift && echo exists || echo missing",
    "exitCode": 0,
    "outputSnippet": "missing\n",
    "timestamp": 1777485282917
  },
  {
    "kind": "edit",
    "toolCallId": "call_sZGqHNkvQRkaW0j1LsndaiAL",
    "path": "ios/project.yml",
    "timestamp": 1777485288611
  },
  {
    "kind": "edit",
    "toolCallId": "call_lKQPXdyxy7S4XKcz5pik0XNV",
    "path": "ios/project.yml",
    "timestamp": 1777485293397
  },
  {
    "kind": "edit",
    "toolCallId": "call_0L9AMj9ip5eqXNyTijdz3rwU",
    "path": "project.yml",
    "timestamp": 1777485298695
  },
  {
    "kind": "edit",
    "toolCallId": "call_duHSZvqbX0ujXPogxwCiArCh",
    "path": "project.yml",
    "timestamp": 1777485302861
  },
  {
    "kind": "write",
    "toolCallId": "call_Gnahx3sjCTSjr9p4b8pNxppv",
    "path": "ios/PrivateMomentsListContinuationTests/PlainTextListContinuationTests.swift",
    "timestamp": 1777485315396
  },
  {
    "kind": "write",
    "toolCallId": "call_vItvekFpWLXhGTxXEGijytqQ",
    "path": "ios/PrivateMoments/Views/PlainTextListEditor.swift",
    "timestamp": 1777485401828
  },
  {
    "kind": "edit",
    "toolCallId": "call_hERzzjX9vG2eNcjhZhnx6ZsS",
    "path": "ios/PrivateMomentsListContinuationTests/PlainTextListContinuationTests.swift",
    "timestamp": 1777485473091
  },
  {
    "kind": "edit",
    "toolCallId": "call_uaZRD07VBiysEJk3Twj07HyC",
    "path": "ios/PrivateMomentsListContinuationTests/PlainTextListContinuationTests.swift",
    "timestamp": 1777485476293
  },
  {
    "kind": "edit",
    "toolCallId": "call_EdneLgnr0X0HwAU98WyWdGXv",
    "path": "ios/PrivateMomentsListContinuationTests/PlainTextListContinuationTests.swift",
    "timestamp": 1777485480000
  },
  {
    "kind": "edit",
    "toolCallId": "call_QpxbyjLmCNVLhoiT4uccK9Bn",
    "path": "ios/PrivateMomentsListContinuationTests/PlainTextListContinuationTests.swift",
    "timestamp": 1777485493883
  },
  {
    "kind": "edit",
    "toolCallId": "call_LL1P8IzfDos9YtJMLWWPbbUv",
    "path": "ios/PrivateMoments/Views/PlainTextListEditor.swift",
    "timestamp": 1777485539986
  },
  {
    "kind": "edit",
    "toolCallId": "call_OEydxZqblePCZzbohhgqs4gI",
    "path": "ios/PrivateMoments/Views/PlainTextListEditor.swift",
    "timestamp": 1777485546786
  }
]
